userrecon/__init__.py
userrecon/platforms.py
userrecon/recon.py
userrecon-1.0.3.dist-info/METADATA
userrecon-1.0.3.dist-info/WHEEL
userrecon-1.0.3.dist-info/entry_points.txt
userrecon-1.0.3.dist-info/top_level.txt
userrecon-1.0.3.dist-info/RECORD
