Metadata-Version: 2.4
Name: userrecon
Version: 1.0.3
Summary: CLI-based OSINT tool for username reconnaissance
Author: CyberWithPriyanshu
Author-email: Cyberwithpriyanshu@gmail.com
Requires-Python: >=3.7
Requires-Dist: requests
Dynamic: author
Dynamic: author-email
Dynamic: description
Dynamic: description-content-type
Dynamic: requires-dist
Dynamic: requires-python
Dynamic: summary
